profiley/__init__.py
profiley/core.py
profiley/einasto.py
profiley/filtering.py
profiley/nfw.py
profiley/numeric.py
profiley/pressure.py
profiley/helpers/__init__.py
profiley/helpers/cosmology.py
profiley/helpers/hankel.py
profiley/helpers/lensing.py
profiley/helpers/lss.py
profiley/helpers/math.py
profiley/helpers/spherical.py
profiley/helpers/decorators/__init__.py
profiley/helpers/decorators/base.py
profiley-1.4.4.dist-info/LICENSE
profiley-1.4.4.dist-info/METADATA
profiley-1.4.4.dist-info/WHEEL
profiley-1.4.4.dist-info/top_level.txt
profiley-1.4.4.dist-info/RECORD
