Metadata-Version: 2.1
Name: profiley
Version: 1.4.4
Summary: Calculation of common astrophysical profiles
Home-page: https://github.com/cristobal-sifon/profiley
Author: Cristobal Sifon
Author-email: cristobal.sifon@pucv.cl
Classifier: Development Status :: 5 - Production/Stable
Classifier: License :: OSI Approved :: MIT License
Classifier: Programming Language :: Python
License-File: LICENSE
Requires-Dist: astropy >=4.0
Requires-Dist: numpy <2.0,>=1.0
Requires-Dist: scipy <2.0,>=1.0
